{
  "_note1": "KEEP THIS FILE! Check it into a version control system (VCS) like git.",
  "_note2": "ObjectBox manages crucial IDs for your object model. See docs for details.",
  "_note3": "If you have VCS merge conflicts, you must resolve them according to ObjectBox docs.",
  "entities": [
    {
      "id": "12:5599323193622370360",
      "lastPropertyId": "3:4112821665472373131",
      "name": "ActivityObject",
      "properties": [
        {
          "id": "1:2905162504185623893",
          "name": "timestamp"
        },
        {
          "id": "2:722396479984037073",
          "name": "Activity"
        },
        {
          "id": "3:4112821665472373131",
          "indexId": "14:3464385012185836571",
          "name": "activityTimeseriesId"
        }
      ],
      "relations": []
    },
    {
      "id": "13:6993245697722759092",
      "lastPropertyId": "3:1929080733143658700",
      "name": "ActivityTimeseries",
      "properties": [
        {
          "id": "1:4541692134599246941",
          "name": "timestamp"
        },
        {
          "id": "2:4121490719935431151",
          "indexId": "15:4294176719410970926",
          "name": "timestamp_day"
        },
        {
          "id": "3:1929080733143658700",
          "name": "uploaded"
        }
      ],
      "relations": []
    },
    {
      "id": "14:856135108886577139",
      "lastPropertyId": "4:1378216828502684547",
      "name": "GLocationsObject",
      "properties": [
        {
          "id": "1:7245019361435482836",
          "name": "timestamp"
        },
        {
          "id": "2:597980022907005384",
          "name": "lat"
        },
        {
          "id": "3:8271318699518839714",
          "name": "lng"
        },
        {
          "id": "4:1378216828502684547",
          "indexId": "16:105787830006592716",
          "name": "gLocationTimeseriesId"
        }
      ],
      "relations": []
    },
    {
      "id": "15:1512318536122334520",
      "lastPropertyId": "3:1454289270521027558",
      "name": "GLocationTimeseries",
      "properties": [
        {
          "id": "1:4108856087842266716",
          "name": "timestamp"
        },
        {
          "id": "2:7661510921669931506",
          "indexId": "17:5292606109852934604",
          "name": "timestamp_day"
        },
        {
          "id": "3:1454289270521027558",
          "name": "uploaded"
        }
      ],
      "relations": []
    },
    {
      "id": "16:7593924127179674554",
      "lastPropertyId": "3:1283962327334215780",
      "name": "NetworkObject",
      "properties": [
        {
          "id": "1:7174725835242585334",
          "name": "timestamp"
        },
        {
          "id": "2:5252704000820905786",
          "name": "networkType"
        },
        {
          "id": "3:1283962327334215780",
          "indexId": "18:7895033073110458923",
          "name": "networkTimeseriesId"
        }
      ],
      "relations": []
    },
    {
      "id": "17:127579443793887856",
      "lastPropertyId": "3:8707046711055330048",
      "name": "NetworkTimeseries",
      "properties": [
        {
          "id": "1:2072685975969423351",
          "name": "timestamp"
        },
        {
          "id": "2:1393378435399776439",
          "indexId": "19:1394887768294782134",
          "name": "timestamp_day"
        },
        {
          "id": "3:8707046711055330048",
          "name": "uploaded"
        }
      ],
      "relations": []
    },
    {
      "id": "18:8758411605812399048",
      "lastPropertyId": "3:2655169756362937007",
      "name": "RunningApplicationObject",
      "properties": [
        {
          "id": "1:1994666807131838363",
          "name": "timestamp"
        },
        {
          "id": "2:1849646944212768582",
          "name": "applicationName"
        },
        {
          "id": "3:2655169756362937007",
          "indexId": "20:1007159208120427739",
          "name": "runningApplicationTimeseriesId"
        }
      ],
      "relations": []
    },
    {
      "id": "19:8360146510486071982",
      "lastPropertyId": "3:3347970233184455320",
      "name": "RunningApplicationTimeseries",
      "properties": [
        {
          "id": "1:147328323361822127",
          "name": "timestamp"
        },
        {
          "id": "2:7623780523062842222",
          "indexId": "21:6941303143748460514",
          "name": "timestamp_day"
        },
        {
          "id": "3:3347970233184455320",
          "name": "uploaded"
        }
      ],
      "relations": []
    },
    {
      "id": "20:3216979828340492205",
      "lastPropertyId": "3:4442092620865122467",
      "name": "ScreenOnObject",
      "properties": [
        {
          "id": "1:9186306222014067256",
          "name": "timestamp"
        },
        {
          "id": "2:216132276594525999",
          "name": "screenOn"
        },
        {
          "id": "3:4442092620865122467",
          "indexId": "22:8880908461882580719",
          "name": "screenOnTimeseriesId"
        }
      ],
      "relations": []
    },
    {
      "id": "21:1342786390968092492",
      "lastPropertyId": "3:3660384802716248076",
      "name": "ScreenOnTimeseries",
      "properties": [
        {
          "id": "1:3188840052333037826",
          "name": "timestamp"
        },
        {
          "id": "2:5318107355138095658",
          "indexId": "23:8637666333707704169",
          "name": "timestamp_day"
        },
        {
          "id": "3:3660384802716248076",
          "name": "uploaded"
        }
      ],
      "relations": []
    },
    {
      "id": "22:3930712039817027007",
      "lastPropertyId": "3:6541707572442129876",
      "name": "TrackObject",
      "properties": [
        {
          "id": "1:2920837440432976936",
          "name": "startTimestamp"
        },
        {
          "id": "2:5608416712466838448",
          "name": "endTimestamp"
        },
        {
          "id": "3:6541707572442129876",
          "indexId": "24:863290451293849632",
          "name": "trackTimeseriesId"
        }
      ],
      "relations": []
    },
    {
      "id": "23:5158038373099840149",
      "lastPropertyId": "3:4705702612758360189",
      "name": "TrackTimeseries",
      "properties": [
        {
          "id": "1:8110513301352678998",
          "name": "timestamp"
        },
        {
          "id": "2:3136863826313706129",
          "indexId": "25:5731662273093176421",
          "name": "timestamp_day"
        },
        {
          "id": "3:4705702612758360189",
          "name": "uploaded"
        }
      ],
      "relations": []
    }
  ],
  "lastEntityId": "23:5158038373099840149",
  "lastIndexId": "25:5731662273093176421",
  "lastRelationId": "0:0",
  "lastSequenceId": "0:0",
  "modelVersion": 4,
  "modelVersionParserMinimum": 4,
  "retiredEntityUids": [
    8578667416844146318,
    554794856199424434,
    1387001295245851897,
    6967655174947100471,
    5145730795305644100,
    6836742050697117276,
    3398124044141454253,
    6824238146016827325,
    7959246809199005750,
    5241043950638552226,
    5942748400008560175
  ],
  "retiredIndexUids": [
    7048056520408944441,
    7114474581703430600,
    4640370968670136603,
    433584984369334737,
    7112975886565926479,
    5242197643884091499,
    4975009078401588147,
    1644523492527717822,
    4149662972134798114,
    588205257721495161,
    7203461495496474023,
    7044656098986646017,
    1603299999421220468
  ],
  "retiredPropertyUids": [
    5037912826216377023,
    1892655852141805668,
    1838428874393279744,
    9151154447523766261,
    3407544841998329155,
    8299656493615012214,
    2277590411919333255,
    177558413883020977,
    4631554893006949621,
    4365996462792813607,
    5055302870108928496,
    2522379065935596435,
    9216805249429586355,
    3795195993090335651,
    8636178038154018983,
    1893269737877590964,
    4285549804724940357,
    5968602226885214496,
    88118222957391441,
    5589241032449896858,
    5604189860498853571,
    2030473453061713089,
    3326066083100248226,
    154354639798689501,
    6030888181059336348,
    475371066371261222,
    5223646243791073180,
    5636523775984349008,
    5039774799349764365,
    9155340132821143657,
    5999478650470744277,
    425359404591393794,
    5609783540215972177,
    5761132066954115896,
    8575275573429177313,
    2278841328083443404,
    1836491279402441651,
    6868415973123200801,
    3466835725973777380,
    2168154149015017617,
    7687076928402406665,
    4633946712034305567,
    1845837952086462776,
    9122090736806118005,
    5356095761643617800,
    6986128659538554106,
    170490338850709279
  ],
  "retiredRelationUids": [],
  "version": 1
}