{
  "_note1": "KEEP THIS FILE! Check it into a version control system (VCS) like git.",
  "_note2": "ObjectBox manages crucial IDs for your object model. See docs for details.",
  "_note3": "If you have VCS merge conflicts, you must resolve them according to ObjectBox docs.",
  "entities": [
    {
      "id": "1:2231102275822883687",
      "lastPropertyId": "8:9033459357256024654",
      "name": "SensorTimeseries",
      "properties": [
        {
          "id": "1:1789519656445653800",
          "indexId": "2:8683188569228289061",
          "name": "timestamp_day"
        },
        {
          "id": "2:2689937162909183090",
          "name": "type"
        },
        {
          "id": "3:6007187772945796179",
          "name": "sensor_id"
        },
        {
          "id": "4:5738199221433580766",
          "name": "user"
        },
        {
          "id": "5:4205825709816197735",
          "name": "timestamp"
        },
        {
          "id": "8:9033459357256024654",
          "indexId": "11:6674818520635382671",
          "name": "sensor_infoId"
        }
      ]
    },
    {
      "id": "3:8736519272169629635",
      "lastPropertyId": "5:3653110271963717736",
      "name": "SensorValue",
      "properties": [
        {
          "id": "1:7156967360505387699",
          "name": "timestamp"
        },
        {
          "id": "5:3653110271963717736",
          "indexId": "12:5900133591604336339",
          "name": "sensor_timeseriesId"
        }
      ]
    },
    {
      "id": "6:8043790786839872650",
      "lastPropertyId": "6:5129955093525124214",
      "name": "SensorInfo",
      "properties": [
        {
          "id": "1:7165058175100612556",
          "name": "sensor_name"
        },
        {
          "id": "2:3942675882933308004",
          "name": "description"
        },
        {
          "id": "6:5129955093525124214",
          "name": "id"
        }
      ]
    },
    {
      "id": "7:3510253158207326883",
      "lastPropertyId": "4:7948359195286906692",
      "name": "StringEntitiy",
      "properties": [
        {
          "id": "1:9202577289243359260",
          "name": "id"
        },
        {
          "id": "2:3538436134943211444",
          "name": "value"
        },
        {
          "id": "4:7948359195286906692",
          "indexId": "13:1988049912238741435",
          "name": "sensor_valueId"
        }
      ]
    },
    {
      "id": "8:2708872204759566452",
      "lastPropertyId": "6:3292395815345258269",
      "name": "ValueInfo",
      "properties": [
        {
          "id": "1:835019631086790433",
          "name": "name"
        },
        {
          "id": "2:944238715736064970",
          "name": "description"
        },
        {
          "id": "3:3905180273580206134",
          "name": "unit"
        },
        {
          "id": "5:9096630506674233945",
          "indexId": "14:7549266287186073401",
          "name": "sensor_infoId"
        },
        {
          "id": "6:3292395815345258269",
          "name": "id"
        }
      ]
    }
  ],
  "lastEntityId": "8:2708872204759566452",
  "lastIndexId": "14:7549266287186073401",
  "lastSequenceId": "0:0",
  "modelVersion": 2,
  "retiredEntityUids": [
    8484266847063080416,
    2725568593564183073,
    2675937856357431152
  ],
  "retiredIndexUids": [
    7027715837607730549,
    3563420295100707051,
    4041125933433039309,
    4908686359240154526,
    7910870947971585880,
    449269585603217441,
    8284951463926411881,
    673056861347610691,
    5080581178085216751
  ],
  "retiredPropertyUids": [
    1469077156708988016,
    5116343578847437068,
    7466115699907384723,
    3520814663004469946,
    6402949675922867884,
    2914963194699129395,
    8930030328274045799,
    5954965432102707301,
    296323719981603051,
    8465152943128798322,
    3704174042079993426,
    1339614846109850964,
    3332072700750127565,
    2236336579726188569,
    1595032974852565096,
    7354706401568768722,
    3010792138395219498,
    6572721573972144763,
    4296460960793358782,
    521909452727172316,
    2000799680838502543,
    8681993767102961773
  ],
  "version": 1
}